poe/__init__.py
poe/aspect.py
poe/elements.py
poe/logger.py
poe/utility.py
page_object_elements-0.4.1.dist-info/METADATA
page_object_elements-0.4.1.dist-info/WHEEL
page_object_elements-0.4.1.dist-info/top_level.txt
page_object_elements-0.4.1.dist-info/RECORD
