Metadata-Version: 2.1
Name: page-object-elements
Version: 0.4.1
Summary: Page Object Elements
Home-page: https://pypi.org/project/page-object-elements/
Author: Ranisavljevic Milan
Author-email: ramdjaram@gmail.com
License: MIT
Classifier: Intended Audience :: Developers
Classifier: License :: OSI Approved :: MIT License
Classifier: Programming Language :: Python
Classifier: Programming Language :: Python :: 3
Classifier: Programming Language :: Python :: 3.6
Classifier: Programming Language :: Python :: 3.7
Classifier: Programming Language :: Python :: 3.8
Classifier: Programming Language :: Python :: 3.9
Classifier: Operating System :: OS Independent
Requires-Dist: selenium
Requires-Dist: psutil
